setup.py
gw_probability/Binomialdistribution.py
gw_probability/Gaussiandistribution.py
gw_probability/Generaldistribution.py
gw_probability/__init__.py
gw_probability.egg-info/PKG-INFO
gw_probability.egg-info/SOURCES.txt
gw_probability.egg-info/dependency_links.txt
gw_probability.egg-info/not-zip-safe
gw_probability.egg-info/top_level.txt