Metadata-Version: 1.0
Name: gw-probability
Version: 0.2
Summary: Gaussian and Binomial distributions
Home-page: UNKNOWN
Author: George Wee
Author-email: UNKNOWN
License: UNKNOWN
Platform: UNKNOWN
